simple_spykes/__init__.py
simple_spykes/graphing/__init__.py
simple_spykes/graphing/basic.py
simple_spykes/graphing/multi.py
simple_spykes/graphing/raw.py
simple_spykes/graphing/util/__init__.py
simple_spykes/graphing/util/graphdata.py
simple_spykes/graphing/util/grapher.py
simple_spykes/graphing/util/io.py
simple_spykes/metric_packages/__init__.py
simple_spykes/metric_packages/bombcell_metrics.py
simple_spykes/metric_packages/ecephys_metrics.py
simple_spykes/metric_packages/spikeinterface_metrics.py
simple_spykes/util/__init__.py
simple_spykes/util/ecephys.py
simple_spykes-0.1.0.dist-info/LICENSE
simple_spykes-0.1.0.dist-info/METADATA
simple_spykes-0.1.0.dist-info/WHEEL
simple_spykes-0.1.0.dist-info/top_level.txt
simple_spykes-0.1.0.dist-info/RECORD
