Metadata-Version: 2.1
Name: simple-spykes
Version: 0.1.0
Summary: Utility library for spike sorting quality metrics
Author: Spencer Hanson
Keywords: neuroscience,spike sorting,tools,science
Classifier: Programming Language :: Python :: 3
License-File: LICENSE
Requires-Dist: forked-ecephys-spike-sorting (==0.1.1)
Requires-Dist: spikeinterface[full] (==0.98.2)
Requires-Dist: numpy
Requires-Dist: matplotlib
Requires-Dist: pendulum
Requires-Dist: probeinterface (==0.2.17)
